PKG-INFO
pyproject.toml
giadep/__init__.py
giadep/__version__.py
giadep/POI_JSON_API/REFRESHTIME_INDEX.json
giadep/POI_JSON_API/all_position.json
giadep/POI_JSON_API/LANGUAGE/en_US.json
giadep/POI_JSON_API/LANGUAGE/fr_FR.json
giadep/POI_JSON_API/LANGUAGE/ja_JP.json
giadep/POI_JSON_API/LANGUAGE/zh_CN.json
giadep/POI_JSON_API/en_US/ID_INDEX.json
giadep/POI_JSON_API/en_US/ITEM_NAME.json
giadep/POI_JSON_API/en_US/dataset/1.json
giadep/POI_JSON_API/en_US/dataset/10.json
giadep/POI_JSON_API/en_US/dataset/11.json
giadep/POI_JSON_API/en_US/dataset/12.json
giadep/POI_JSON_API/en_US/dataset/13.json
giadep/POI_JSON_API/en_US/dataset/14.json
giadep/POI_JSON_API/en_US/dataset/2.json
giadep/POI_JSON_API/en_US/dataset/3.json
giadep/POI_JSON_API/en_US/dataset/4.json
giadep/POI_JSON_API/en_US/dataset/5.json
giadep/POI_JSON_API/en_US/dataset/6.json
giadep/POI_JSON_API/en_US/dataset/7.json
giadep/POI_JSON_API/en_US/dataset/8.json
giadep/POI_JSON_API/en_US/dataset/9.json
giadep/POI_JSON_API/en_US/dataset/area.json
giadep/POI_JSON_API/en_US/dataset/icon.json
giadep/POI_JSON_API/en_US/dataset/id_stamp.json
giadep/POI_JSON_API/en_US/dataset/item.json
giadep/POI_JSON_API/en_US/dataset/type.json
giadep/POI_JSON_API/zh_CN/ID_INDEX.json
giadep/POI_JSON_API/zh_CN/ITEM_NAME.json
giadep/POI_JSON_API/zh_CN/dataset/1.json
giadep/POI_JSON_API/zh_CN/dataset/10.json
giadep/POI_JSON_API/zh_CN/dataset/11.json
giadep/POI_JSON_API/zh_CN/dataset/12.json
giadep/POI_JSON_API/zh_CN/dataset/13.json
giadep/POI_JSON_API/zh_CN/dataset/14.json
giadep/POI_JSON_API/zh_CN/dataset/2.json
giadep/POI_JSON_API/zh_CN/dataset/3.json
giadep/POI_JSON_API/zh_CN/dataset/4.json
giadep/POI_JSON_API/zh_CN/dataset/5.json
giadep/POI_JSON_API/zh_CN/dataset/6.json
giadep/POI_JSON_API/zh_CN/dataset/7.json
giadep/POI_JSON_API/zh_CN/dataset/8.json
giadep/POI_JSON_API/zh_CN/dataset/9.json
giadep/POI_JSON_API/zh_CN/dataset/area.json
giadep/POI_JSON_API/zh_CN/dataset/icon.json
giadep/POI_JSON_API/zh_CN/dataset/id_stamp.json
giadep-0.0.2.dist-info/METADATA
giadep-0.0.2.dist-info/WHEEL
giadep-0.0.2.dist-info/RECORD
