Metadata-Version: 2.1
Name: giadep
Version: 0.0.2
Summary: Dependence for GIA.
Author: Infstellar
Classifier: License :: OSI Approved :: MIT License
Classifier: Operating System :: OS Independent
Classifier: Programming Language :: Python :: 3
Requires-Python: >=3.7
